rapidapi_mcp_server/__init__.py
rapidapi_mcp_server/chrome_client.py
rapidapi_mcp_server/enhanced_chrome_client.py
rapidapi_mcp_server/server.py
rapidapi_mcp_server-1.3.1.dist-info/licenses/LICENSE
rapidapi_mcp_server-1.3.1.dist-info/METADATA
rapidapi_mcp_server-1.3.1.dist-info/WHEEL
rapidapi_mcp_server-1.3.1.dist-info/entry_points.txt
rapidapi_mcp_server-1.3.1.dist-info/top_level.txt
rapidapi_mcp_server-1.3.1.dist-info/RECORD
