Metadata-Version: 2.4
Name: rapidapi-mcp-server
Version: 1.3.1
Summary: RapidAPI marketplace discovery and assessment MCP server using undetected-chromedriver for anti-bot detection bypass
Author-email: Andrew Lewin <andrewlwn77@users.noreply.github.com>
License: MIT
Project-URL: Homepage, https://github.com/andrewlwn77/rapidapi-mcp-server
Project-URL: Repository, https://github.com/andrewlwn77/rapidapi-mcp-server.git
Project-URL: Issues, https://github.com/andrewlwn77/rapidapi-mcp-server/issues
Project-URL: Documentation, https://github.com/andrewlwn77/rapidapi-mcp-server#readme
Project-URL: Changelog, https://github.com/andrewlwn77/rapidapi-mcp-server/blob/main/CHANGELOG.md
Keywords: mcp,rapidapi,api,discovery,chrome,automation,claude,ai
Classifier: Development Status :: 4 - Beta
Classifier: Intended Audience :: Developers
Classifier: Topic :: Software Development :: Libraries :: Python Modules
Classifier: Topic :: Internet :: WWW/HTTP :: Browsers
Classifier: Topic :: System :: Networking
Classifier: Programming Language :: Python :: 3
Classifier: Programming Language :: Python :: 3.8
Classifier: Programming Language :: Python :: 3.9
Classifier: Programming Language :: Python :: 3.10
Classifier: Programming Language :: Python :: 3.11
Classifier: Programming Language :: Python :: 3.12
Classifier: Operating System :: OS Independent
Classifier: Environment :: Console
Classifier: Framework :: AsyncIO
Requires-Python: >=3.8
License-File: LICENSE
Requires-Dist: mcp>=1.0.0
Requires-Dist: undetected-chromedriver>=3.5.0
Requires-Dist: selenium>=4.15.0
Requires-Dist: beautifulsoup4>=4.12.0
Requires-Dist: python-dotenv>=1.0.0
Requires-Dist: aiohttp>=3.8.0
Requires-Dist: typing-extensions>=4.0.0
Provides-Extra: dev
Requires-Dist: pytest>=7.0.0; extra == "dev"
Requires-Dist: pytest-asyncio>=0.21.0; extra == "dev"
Requires-Dist: black>=23.0.0; extra == "dev"
Requires-Dist: isort>=5.12.0; extra == "dev"
Requires-Dist: mypy>=1.0.0; extra == "dev"
Requires-Dist: ruff>=0.1.0; extra == "dev"
Dynamic: license-file
